pythonc/__init__.py
pythonc/pythonc.py
sdbit04_pythonc-1.2.2.dist-info/METADATA
sdbit04_pythonc-1.2.2.dist-info/WHEEL
sdbit04_pythonc-1.2.2.dist-info/entry_points.txt
sdbit04_pythonc-1.2.2.dist-info/top_level.txt
sdbit04_pythonc-1.2.2.dist-info/RECORD
