Metadata-Version: 2.1
Name: sdbit04-pythonc
Version: 1.2.2
Summary: On installation, This package gives a command pythonc to compile any python module
Home-page: https://github.com/
Author: swapankumarDas
License: MIT
Platform: UNKNOWN
Classifier: License :: OSI Approved :: MIT License
